logflake/__init__.py
logflake/logflake.py
logflake-1.2.1.dist-info/METADATA
logflake-1.2.1.dist-info/WHEEL
logflake-1.2.1.dist-info/top_level.txt
logflake-1.2.1.dist-info/RECORD
