Metadata-Version: 2.1
Name: logflake
Version: 1.2.1
Summary: LogFlake Python Client
Author-email: CloudPhoenix Srl <info@cloudphoenix.it>
Project-URL: Homepage, https://github.com/CloudPhoenix/logflake-client-python
Keywords: logflake
Requires-Python: >=3.8
Requires-Dist: requests
Requires-Dist: snappy
Provides-Extra: dev
Requires-Dist: pip-tools ; extra == 'dev'
